 { "type": "FeatureCollection",
 	"id": "@id",
 	"crs": {"type": "___", "name": "wgs84"},
 	"projection": {"atom": "year"},
  "features": [
      { "type": "Feature",
      	"id": "@id",
      	"label": "Massachusetts",
      	"contexts": [
		    { "geometry": {"type": "Point", "coordinates": [72.0, 42.5]},
		      "when": [ {"s": "1630", "e": "1691" } ],
		      "properties": {"name": "Massachusetts Bay Colony", "note": "__"}
		    }, {
		      "geometry": {"type": "Point", "coordinates": [74.0, 41.5]},
		      "when": [ {"s": "1691", "e": "1776" } ],
		      "properties": {"name": "Province of Massachusetts Bay", "note": "__"}
		    }, {
		      "geometry": {"type": "Point", "coordinates": [70.0, 40.5]},
		      "when": [ {"s": "1776" } ],
		      "properties": {"name": "Commonwealth of Massachusetts", "note": "__"}
		    }
      	]
      }, { 
      	"type": "Period",
        "geometry": {"type": "Point", "coordinates": [102.0, 0.5]},
        "when": [ {"s":"__", "ls":"__", "ee":"__", "e":"__" } ],
        "properties": {"prop0": "value0"}
        }
      ]
 }